fpm/__init__.py
fpm/__main__.py
fpm/_version.py
fpm/fpm
fpm.libs/libgcc_s-887de51c.so.1
fpm.libs/libgfortran-d29565f3.so.5.0.0
fpm.libs/libgomp-24921df4.so.1.0.0
fpm.libs/libquadmath-79b02236.so.0.0.0
fpm-0.12.0.dist-info/METADATA
fpm-0.12.0.dist-info/WHEEL
fpm-0.12.0.dist-info/entry_points.txt
fpm-0.12.0.dist-info/top_level.txt
fpm-0.12.0.dist-info/licenses/LICENSE
fpm-0.12.0.dist-info/RECORD
