Metadata-Version: 2.4
Name: fpm
Version: 0.12.0
Summary: Fortran package manager
Author: fpm maintainers
License-Expression: MIT
Project-URL: homepage, https://fpm.fortran-lang.org
Project-URL: source-code, https://github.com/fortran-lang/fpm
Project-URL: bug-tracker, https://github.com/fortran-lang/fpm/issues
Keywords: fpm,fortran,package manager
Classifier: Development Status :: 3 - Alpha
Classifier: Intended Audience :: Developers
Classifier: Operating System :: OS Independent
Classifier: Programming Language :: Fortran
Classifier: Topic :: Software Development :: Build Tools
Classifier: Topic :: Software Development :: Compilers
Classifier: Topic :: Software Development :: Pre-processors
Classifier: Topic :: Utilities
Requires-Python: >=3.7
License-File: LICENSE
Dynamic: license-file
